{
  "meta" : {
    "name" : "Medium Ship with Cannons",
    "creator" : "Peefio",
    "createDate" : "Tue Dec 16 11:14:04 EST 2014",
    "plansClass" : "com.someguyssoftware.plans.ConnectorPlans",
    "comments" : "Modified by gottsch",
    "version" : "2.0"
  },
  "height" : 21,
  "depth" : 11,
  "width" : 22,
  "preservePlansAir" : false,
  "substituteWithAir" : [35],
  "preserveWorldWater" : false,
  "preserveWorldLava" : false,
  "preserveWorldPlants" : false,
  "verticalOffset" : 0,
  "postProcess" : [
    50,
    69,
    77,
    143
  ],
  "rules" : {
    "0" : {
      "ruleId" : 0,
      "blockId" : 0,
      "blockName" : "",
      "metaId" : 0,
      "probability" : 100,
      "substituteId" : -1,
      "substituteName" : "",
      "spawns" : [ ]
    },
    "1" : {
      "ruleId" : 1,
      "blockId" : 164,
      "blockName" : "",
      "metaId" : 4,
      "probability" : 100,
      "substituteId" : -1,
      "substituteName" : "",
      "spawns" : [ ]
    },
    "2" : {
      "ruleId" : 2,
      "blockId" : 17,
      "blockName" : "",
      "metaId" : 5,
      "probability" : 100,
      "substituteId" : -1,
      "substituteName" : "",
      "spawns" : [ ]
    },
    "3" : {
      "ruleId" : 3,
      "blockId" : 164,
      "blockName" : "",
      "metaId" : 5,
      "probability" : 100,
      "substituteId" : -1,
      "substituteName" : "",
      "spawns" : [ ]
    },
    "4" : {
      "ruleId" : 4,
      "blockId" : 5,
      "blockName" : "",
      "metaId" : 0,
      "probability" : 100,
      "substituteId" : -1,
      "substituteName" : "",
      "spawns" : [ ]
    },
    "5" : {
      "ruleId" : 5,
      "blockId" : 5,
      "blockName" : "",
      "metaId" : 5,
      "probability" : 100,
      "substituteId" : -1,
      "substituteName" : "",
      "spawns" : [ ]
    },
    "6" : {
      "ruleId" : 6,
      "blockId" : 17,
      "blockName" : "",
      "metaId" : 1,
      "probability" : 100,
      "substituteId" : -1,
      "substituteName" : "",
      "spawns" : [ ]
    },
    "7" : {
      "ruleId" : 7,
      "blockId" : 35,
      "blockName" : "",
      "metaId" : 0,
      "probability" : 100,
      "substituteId" : -1,
      "substituteName" : "",
      "spawns" : [ ]
    },
    "8" : {
      "ruleId" : 8,
      "blockId" : 65,
      "blockName" : "",
      "metaId" : 3,
      "probability" : 100,
      "substituteId" : -1,
      "substituteName" : "",
      "spawns" : [ ]
    },
    "9" : {
      "ruleId" : 9,
      "blockId" : 52,
      "blockName" : "",
      "metaId" : 0,
      "probability" : 100,
      "substituteId" : -1,
      "substituteName" : "",
      "spawns" : ["Skeleton", "Zombie"]
    },
    "10" : {
      "ruleId" : 10,
      "blockId" : 65,
      "blockName" : "",
      "metaId" : 2,
      "probability" : 100,
      "substituteId" : -1,
      "substituteName" : "",
      "spawns" : [ ]
    },
    "11" : {
      "ruleId" : 11,
      "blockId" : 54,
      "blockName" : "",
      "metaId" : 5,
      "probability" : 100,
      "substituteId" : -1,
      "substituteName" : "",
      "spawns" : [ ]
    },
    "12" : {
      "ruleId" : 12,
      "blockId" : 17,
      "blockName" : "",
      "metaId" : 9,
      "probability" : 100,
      "substituteId" : -1,
      "substituteName" : "",
      "spawns" : [ ]
    },
    "13" : {
      "ruleId" : 13,
      "blockId" : 85,
      "blockName" : "",
      "metaId" : 0,
      "probability" : 100,
      "substituteId" : -1,
      "substituteName" : "",
      "spawns" : [ ]
    },
    "14" : {
      "ruleId" : 14,
      "blockId" : 77,
      "blockName" : "",
      "metaId" : 4,
      "probability" : 100,
      "substituteId" : -1,
      "substituteName" : "",
      "spawns" : [ ]
    },
    "15" : {
      "ruleId" : 15,
      "blockId" : 1,
      "blockName" : "",
      "metaId" : 0,
      "probability" : 100,
      "substituteId" : -1,
      "substituteName" : "",
      "spawns" : [ ]
    },
    "17" : {
      "ruleId" : 17,
      "blockId" : 134,
      "blockName" : "",
      "metaId" : 4,
      "probability" : 100,
      "substituteId" : -1,
      "substituteName" : "",
      "spawns" : [ ]
    },
    "16" : {
      "ruleId" : 16,
      "blockId" : 134,
      "blockName" : "",
      "metaId" : 5,
      "probability" : 100,
      "substituteId" : -1,
      "substituteName" : "",
      "spawns" : [ ]
    },
    "19" : {
      "ruleId" : 19,
      "blockId" : 164,
      "blockName" : "",
      "metaId" : 3,
      "probability" : 100,
      "substituteId" : -1,
      "substituteName" : "",
      "spawns" : [ ]
    },
    "18" : {
      "ruleId" : 18,
      "blockId" : 134,
      "blockName" : "",
      "metaId" : 1,
      "probability" : 100,
      "substituteId" : -1,
      "substituteName" : "",
      "spawns" : [ ]
    },
    "21" : {
      "ruleId" : 21,
      "blockId" : 17,
      "blockName" : "",
      "metaId" : 10,
      "probability" : 100,
      "substituteId" : -1,
      "substituteName" : "",
      "spawns" : [ ]
    },
    "20" : {
      "ruleId" : 20,
      "blockId" : 96,
      "blockName" : "",
      "metaId" : 1,
      "probability" : 100,
      "substituteId" : -1,
      "substituteName" : "",
      "spawns" : [ ]
    },
    "23" : {
      "ruleId" : 23,
      "blockId" : 164,
      "blockName" : "",
      "metaId" : 1,
      "probability" : 100,
      "substituteId" : -1,
      "substituteName" : "",
      "spawns" : [ ]
    },
    "22" : {
      "ruleId" : 22,
      "blockId" : 5,
      "blockName" : "",
      "metaId" : 1,
      "probability" : 100,
      "substituteId" : -1,
      "substituteName" : "",
      "spawns" : [ ]
    },
    "25" : {
      "ruleId" : 25,
      "blockId" : 96,
      "blockName" : "",
      "metaId" : 0,
      "probability" : 100,
      "substituteId" : -1,
      "substituteName" : "",
      "spawns" : [ ]
    },
    "24" : {
      "ruleId" : 24,
      "blockId" : 164,
      "blockName" : "",
      "metaId" : 2,
      "probability" : 100,
      "substituteId" : -1,
      "substituteName" : "",
      "spawns" : [ ]
    },
    "27" : {
      "ruleId" : 27,
      "blockId" : 69,
      "blockName" : "",
      "metaId" : 5,
      "probability" : 100,
      "substituteId" : -1,
      "substituteName" : "",
      "spawns" : [ ]
    },
    "26" : {
      "ruleId" : 26,
      "blockId" : 77,
      "blockName" : "",
      "metaId" : 3,
      "probability" : 100,
      "substituteId" : -1,
      "substituteName" : "",
      "spawns" : [ ]
    },
    "29" : {
      "ruleId" : 29,
      "blockId" : 102,
      "blockName" : "",
      "metaId" : 0,
      "probability" : 100,
      "substituteId" : -1,
      "substituteName" : "",
      "spawns" : [ ]
    },
    "28" : {
      "ruleId" : 28,
      "blockId" : 134,
      "blockName" : "",
      "metaId" : 0,
      "probability" : 100,
      "substituteId" : -1,
      "substituteName" : "",
      "spawns" : [ ]
    },
    "31" : {
      "ruleId" : 31,
      "blockId" : 50,
      "blockName" : "",
      "metaId" : 2,
      "probability" : 100,
      "substituteId" : -1,
      "substituteName" : "",
      "spawns" : [ ]
    },
    "30" : {
      "ruleId" : 30,
      "blockId" : 69,
      "blockName" : "",
      "metaId" : 13,
      "probability" : 100,
      "substituteId" : -1,
      "substituteName" : "",
      "spawns" : [ ]
    },
    "34" : {
      "ruleId" : 34,
      "blockId" : 126,
      "blockName" : "",
      "metaId" : 8,
      "probability" : 100,
      "substituteId" : -1,
      "substituteName" : "",
      "spawns" : [ ]
    },
    "32" : {
      "ruleId" : 32,
      "blockId" : 164,
      "blockName" : "",
      "metaId" : 0,
      "probability" : 100,
      "substituteId" : -1,
      "substituteName" : "",
      "spawns" : [ ]
    },
    "33" : {
      "ruleId" : 33,
      "blockId" : 96,
      "blockName" : "",
      "metaId" : 7,
      "probability" : 100,
      "substituteId" : -1,
      "substituteName" : "",
      "spawns" : [ ]
    }
  },
  "blockMap" : [
    [
      [
        0,
        0,
        0,
        0,
        0,
        0,
        0,
        0,
        0,
        0,
        0,
        0,
        0,
        0,
        0,
        0,
        0,
        0,
        0,
        0,
        0,
        0
      ],
      [
        0,
        0,
        0,
        0,
        0,
        0,
        0,
        0,
        0,
        0,
        0,
        0,
        0,
        0,
        0,
        0,
        0,
        0,
        0,
        0,
        0,
        0
      ],
      [
        0,
        0,
        0,
        0,
        0,
        0,
        0,
        0,
        0,
        0,
        0,
        0,
        0,
        0,
        0,
        0,
        0,
        0,
        0,
        0,
        0,
        0
      ],
      [
        0,
        0,
        0,
        0,
        0,
        0,
        0,
        0,
        0,
        0,
        0,
        0,
        0,
        0,
        0,
        0,
        0,
        0,
        0,
        0,
        0,
        0
      ],
      [
        0,
        0,
        0,
        0,
        0,
        0,
        0,
        0,
        0,
        0,
        0,
        0,
        0,
        0,
        0,
        0,
        0,
        0,
        0,
        0,
        0,
        0
      ],
      [
        0,
        0,
        0,
        0,
        0,
        0,
        0,
        0,
        1,
        2,
        2,
        2,
        2,
        2,
        2,
        2,
        2,
        2,
        2,
        2,
        2,
        3
      ],
      [
        0,
        0,
        0,
        0,
        0,
        0,
        0,
        0,
        0,
        0,
        0,
        0,
        0,
        0,
        0,
        0,
        0,
        0,
        0,
        0,
        0,
        0
      ],
      [
        0,
        0,
        0,
        0,
        0,
        0,
        0,
        0,
        0,
        0,
        0,
        0,
        0,
        0,
        0,
        0,
        0,
        0,
        0,
        0,
        0,
        0
      ],
      [
        0,
        0,
        0,
        0,
        0,
        0,
        0,
        0,
        0,
        0,
        0,
        0,
        0,
        0,
        0,
        0,
        0,
        0,
        0,
        0,
        0,
        0
      ],
      [
        0,
        0,
        0,
        0,
        0,
        0,
        0,
        0,
        0,
        0,
        0,
        0,
        0,
        0,
        0,
        0,
        0,
        0,
        0,
        0,
        0,
        0
      ],
      [
        0,
        0,
        0,
        0,
        0,
        0,
        0,
        0,
        0,
        0,
        0,
        0,
        0,
        0,
        0,
        0,
        0,
        0,
        0,
        0,
        0,
        0
      ]
    ],
    [
      [
        0,
        0,
        0,
        0,
        0,
        0,
        0,
        0,
        0,
        0,
        0,
        0,
        0,
        0,
        0,
        0,
        0,
        0,
        0,
        0,
        0,
        0
      ],
      [
        0,
        0,
        0,
        0,
        0,
        0,
        0,
        0,
        0,
        0,
        0,
        0,
        0,
        0,
        0,
        0,
        0,
        0,
        0,
        0,
        0,
        0
      ],
      [
        0,
        0,
        0,
        0,
        0,
        0,
        0,
        0,
        0,
        0,
        0,
        0,
        0,
        0,
        0,
        0,
        0,
        0,
        0,
        0,
        0,
        0
      ],
      [
        0,
        0,
        0,
        0,
        0,
        0,
        0,
        0,
        0,
        0,
        4,
        4,
        4,
        4,
        4,
        4,
        4,
        4,
        4,
        4,
        0,
        0
      ],
      [
        0,
        0,
        0,
        0,
        0,
        0,
        0,
        0,
        0,
        4,
        4,
        4,
        4,
        4,
        4,
        4,
        4,
        4,
        4,
        4,
        4,
        0
      ],
      [
        0,
        0,
        0,
        0,
        0,
        0,
        0,
        1,
        5,
        4,
        4,
        4,
        4,
        4,
        4,
        4,
        4,
        4,
        4,
        4,
        4,
        6
      ],
      [
        0,
        0,
        0,
        0,
        0,
        0,
        0,
        0,
        0,
        4,
        4,
        4,
        4,
        4,
        4,
        4,
        4,
        4,
        4,
        4,
        4,
        0
      ],
      [
        0,
        0,
        0,
        0,
        0,
        0,
        0,
        0,
        0,
        0,
        4,
        4,
        4,
        4,
        4,
        4,
        4,
        4,
        4,
        4,
        0,
        0
      ],
      [
        0,
        0,
        0,
        0,
        0,
        0,
        0,
        0,
        0,
        0,
        0,
        0,
        0,
        0,
        0,
        0,
        0,
        0,
        0,
        0,
        0,
        0
      ],
      [
        0,
        0,
        0,
        0,
        0,
        0,
        0,
        0,
        0,
        0,
        0,
        0,
        0,
        0,
        0,
        0,
        0,
        0,
        0,
        0,
        0,
        0
      ],
      [
        0,
        0,
        0,
        0,
        0,
        0,
        0,
        0,
        0,
        0,
        0,
        0,
        0,
        0,
        0,
        0,
        0,
        0,
        0,
        0,
        0,
        0
      ]
    ],
    [
      [
        0,
        0,
        0,
        0,
        0,
        0,
        0,
        0,
        0,
        0,
        0,
        0,
        0,
        0,
        0,
        0,
        0,
        0,
        0,
        0,
        0,
        0
      ],
      [
        0,
        0,
        0,
        0,
        0,
        0,
        0,
        0,
        0,
        0,
        0,
        0,
        0,
        0,
        0,
        0,
        0,
        0,
        0,
        0,
        0,
        0
      ],
      [
        0,
        0,
        0,
        0,
        0,
        0,
        0,
        0,
        0,
        0,
        0,
        4,
        4,
        4,
        4,
        4,
        4,
        4,
        4,
        4,
        0,
        0
      ],
      [
        0,
        0,
        0,
        0,
        0,
        0,
        0,
        0,
        0,
        4,
        4,
        7,
        7,
        7,
        7,
        7,
        7,
        7,
        8,
        4,
        4,
        0
      ],
      [
        0,
        0,
        0,
        0,
        0,
        0,
        0,
        0,
        4,
        7,
        7,
        7,
        7,
        7,
        7,
        7,
        7,
        7,
        7,
        7,
        7,
        4
      ],
      [
        0,
        0,
        0,
        0,
        0,
        0,
        1,
        5,
        4,
        9,
        7,
        7,
        7,
        7,
        7,
        7,
        7,
        7,
        7,
        7,
        7,
        6
      ],
      [
        0,
        0,
        0,
        0,
        0,
        0,
        0,
        0,
        4,
        7,
        7,
        7,
        7,
        7,
        7,
        7,
        7,
        7,
        7,
        7,
        7,
        4
      ],
      [
        0,
        0,
        0,
        0,
        0,
        0,
        0,
        0,
        0,
        4,
        4,
        7,
        7,
        7,
        7,
        7,
        7,
        7,
        10,
        4,
        4,
        0
      ],
      [
        0,
        0,
        0,
        0,
        0,
        0,
        0,
        0,
        0,
        0,
        0,
        4,
        4,
        4,
        4,
        4,
        4,
        4,
        4,
        4,
        0,
        0
      ],
      [
        0,
        0,
        0,
        0,
        0,
        0,
        0,
        0,
        0,
        0,
        0,
        0,
        0,
        0,
        0,
        0,
        0,
        0,
        0,
        0,
        0,
        0
      ],
      [
        0,
        0,
        0,
        0,
        0,
        0,
        0,
        0,
        0,
        0,
        0,
        0,
        0,
        0,
        0,
        0,
        0,
        0,
        0,
        0,
        0,
        0
      ]
    ],
    [
      [
        0,
        0,
        0,
        0,
        0,
        0,
        0,
        0,
        0,
        0,
        0,
        0,
        0,
        0,
        0,
        0,
        0,
        0,
        0,
        0,
        0,
        0
      ],
      [
        0,
        0,
        0,
        0,
        0,
        0,
        0,
        0,
        0,
        0,
        0,
        0,
        0,
        0,
        0,
        0,
        0,
        0,
        0,
        0,
        0,
        0
      ],
      [
        0,
        0,
        0,
        0,
        0,
        0,
        0,
        0,
        0,
        0,
        4,
        4,
        4,
        4,
        4,
        4,
        4,
        4,
        4,
        4,
        0,
        0
      ],
      [
        0,
        0,
        0,
        0,
        0,
        0,
        0,
        0,
        4,
        4,
        7,
        7,
        7,
        7,
        7,
        7,
        7,
        7,
        8,
        7,
        4,
        4
      ],
      [
        0,
        0,
        0,
        0,
        0,
        0,
        0,
        4,
        7,
        7,
        7,
        7,
        7,
        7,
        7,
        7,
        7,
        7,
        7,
        7,
        7,
        4
      ],
      [
        0,
        0,
        0,
        0,
        0,
        0,
        5,
        4,
        11,
        7,
        7,
        7,
        7,
        7,
        7,
        7,
        7,
        7,
        7,
        7,
        7,
        6
      ],
      [
        0,
        0,
        0,
        0,
        0,
        0,
        0,
        4,
        7,
        7,
        7,
        7,
        7,
        7,
        7,
        7,
        7,
        7,
        7,
        7,
        7,
        4
      ],
      [
        0,
        0,
        0,
        0,
        0,
        0,
        0,
        0,
        4,
        4,
        7,
        7,
        7,
        7,
        7,
        7,
        7,
        7,
        10,
        7,
        4,
        4
      ],
      [
        0,
        0,
        0,
        0,
        0,
        0,
        0,
        0,
        0,
        0,
        4,
        4,
        4,
        4,
        4,
        4,
        4,
        4,
        4,
        4,
        0,
        0
      ],
      [
        0,
        0,
        0,
        0,
        0,
        0,
        0,
        0,
        0,
        0,
        0,
        0,
        0,
        0,
        0,
        0,
        0,
        0,
        0,
        0,
        0,
        0
      ],
      [
        0,
        0,
        0,
        0,
        0,
        0,
        0,
        0,
        0,
        0,
        0,
        0,
        0,
        0,
        0,
        0,
        0,
        0,
        0,
        0,
        0,
        0
      ]
    ],
    [
      [
        0,
        0,
        0,
        0,
        0,
        0,
        0,
        0,
        0,
        0,
        0,
        0,
        0,
        0,
        0,
        0,
        0,
        0,
        0,
        0,
        0,
        0
      ],
      [
        0,
        0,
        0,
        0,
        0,
        0,
        0,
        0,
        0,
        0,
        0,
        0,
        0,
        0,
        0,
        0,
        0,
        0,
        0,
        0,
        0,
        0
      ],
      [
        0,
        0,
        0,
        0,
        0,
        0,
        0,
        0,
        0,
        0,
        4,
        4,
        4,
        4,
        4,
        4,
        4,
        4,
        4,
        4,
        4,
        0
      ],
      [
        0,
        0,
        0,
        0,
        0,
        0,
        0,
        0,
        4,
        4,
        7,
        7,
        7,
        7,
        7,
        7,
        7,
        7,
        8,
        7,
        4,
        4
      ],
      [
        0,
        0,
        0,
        0,
        0,
        0,
        4,
        4,
        7,
        7,
        7,
        7,
        7,
        7,
        7,
        7,
        7,
        7,
        7,
        7,
        7,
        4
      ],
      [
        0,
        0,
        0,
        0,
        0,
        1,
        5,
        4,
        7,
        7,
        7,
        7,
        7,
        7,
        7,
        7,
        7,
        7,
        7,
        7,
        7,
        6
      ],
      [
        0,
        0,
        0,
        0,
        0,
        0,
        4,
        4,
        7,
        7,
        7,
        7,
        7,
        7,
        7,
        7,
        7,
        7,
        7,
        7,
        7,
        4
      ],
      [
        0,
        0,
        0,
        0,
        0,
        0,
        0,
        0,
        4,
        4,
        7,
        7,
        7,
        7,
        7,
        7,
        7,
        7,
        10,
        7,
        4,
        4
      ],
      [
        0,
        0,
        0,
        0,
        0,
        0,
        0,
        0,
        0,
        0,
        4,
        4,
        4,
        4,
        4,
        4,
        4,
        4,
        4,
        4,
        4,
        0
      ],
      [
        0,
        0,
        0,
        0,
        0,
        0,
        0,
        0,
        0,
        0,
        0,
        0,
        0,
        0,
        0,
        0,
        0,
        0,
        0,
        0,
        0,
        0
      ],
      [
        0,
        0,
        0,
        0,
        0,
        0,
        0,
        0,
        0,
        0,
        0,
        0,
        0,
        0,
        0,
        0,
        0,
        0,
        0,
        0,
        0,
        0
      ]
    ],
    [
      [
        0,
        0,
        0,
        0,
        0,
        0,
        0,
        0,
        0,
        0,
        0,
        0,
        0,
        0,
        0,
        0,
        0,
        0,
        0,
        0,
        0,
        0
      ],
      [
        0,
        0,
        0,
        0,
        0,
        0,
        0,
        0,
        0,
        0,
        0,
        0,
        0,
        0,
        0,
        0,
        0,
        0,
        0,
        0,
        0,
        0
      ],
      [
        0,
        0,
        0,
        0,
        0,
        0,
        0,
        0,
        0,
        0,
        2,
        2,
        2,
        2,
        2,
        2,
        2,
        2,
        2,
        2,
        2,
        0
      ],
      [
        0,
        0,
        0,
        0,
        0,
        0,
        0,
        0,
        2,
        2,
        4,
        4,
        4,
        4,
        4,
        4,
        4,
        4,
        8,
        4,
        4,
        12
      ],
      [
        0,
        0,
        0,
        0,
        0,
        13,
        2,
        2,
        4,
        4,
        4,
        4,
        4,
        4,
        4,
        4,
        4,
        4,
        4,
        4,
        4,
        12
      ],
      [
        0,
        0,
        0,
        0,
        1,
        2,
        4,
        4,
        4,
        4,
        4,
        4,
        4,
        4,
        4,
        4,
        4,
        4,
        4,
        4,
        4,
        6
      ],
      [
        0,
        0,
        0,
        0,
        0,
        13,
        2,
        2,
        4,
        4,
        4,
        4,
        4,
        4,
        4,
        4,
        4,
        4,
        4,
        4,
        4,
        12
      ],
      [
        0,
        0,
        0,
        0,
        0,
        0,
        0,
        0,
        2,
        2,
        4,
        4,
        4,
        4,
        4,
        4,
        4,
        4,
        10,
        4,
        4,
        12
      ],
      [
        0,
        0,
        0,
        0,
        0,
        0,
        0,
        0,
        0,
        0,
        2,
        2,
        2,
        2,
        2,
        2,
        2,
        2,
        2,
        2,
        2,
        0
      ],
      [
        0,
        0,
        0,
        0,
        0,
        0,
        0,
        0,
        0,
        0,
        0,
        0,
        0,
        0,
        0,
        0,
        0,
        0,
        0,
        0,
        0,
        0
      ],
      [
        0,
        0,
        0,
        0,
        0,
        0,
        0,
        0,
        0,
        0,
        0,
        0,
        0,
        0,
        0,
        0,
        0,
        0,
        0,
        0,
        0,
        0
      ]
    ],
    [
      [
        0,
        0,
        0,
        0,
        0,
        0,
        0,
        0,
        0,
        0,
        0,
        14,
        0,
        0,
        0,
        0,
        0,
        0,
        0,
        0,
        0,
        0
      ],
      [
        0,
        0,
        0,
        0,
        0,
        0,
        0,
        0,
        0,
        0,
        0,
        15,
        0,
        0,
        0,
        0,
        0,
        0,
        0,
        0,
        0,
        0
      ],
      [
        0,
        0,
        0,
        0,
        0,
        0,
        0,
        0,
        0,
        0,
        16,
        15,
        16,
        16,
        0,
        17,
        18,
        6,
        4,
        4,
        4,
        0
      ],
      [
        0,
        0,
        0,
        0,
        0,
        0,
        0,
        0,
        16,
        16,
        0,
        19,
        0,
        0,
        0,
        0,
        0,
        4,
        20,
        7,
        7,
        4
      ],
      [
        0,
        0,
        0,
        21,
        13,
        13,
        22,
        16,
        0,
        0,
        0,
        0,
        0,
        0,
        0,
        0,
        0,
        4,
        7,
        7,
        7,
        4
      ],
      [
        0,
        0,
        0,
        21,
        2,
        2,
        23,
        0,
        0,
        0,
        0,
        0,
        0,
        6,
        0,
        0,
        0,
        0,
        0,
        7,
        7,
        6
      ],
      [
        0,
        0,
        0,
        21,
        13,
        13,
        22,
        16,
        0,
        0,
        0,
        0,
        0,
        0,
        0,
        0,
        0,
        4,
        7,
        7,
        7,
        4
      ],
      [
        0,
        0,
        0,
        0,
        0,
        0,
        0,
        0,
        16,
        16,
        0,
        24,
        0,
        0,
        0,
        0,
        0,
        4,
        25,
        7,
        7,
        4
      ],
      [
        0,
        0,
        0,
        0,
        0,
        0,
        0,
        0,
        0,
        0,
        16,
        15,
        16,
        16,
        0,
        17,
        18,
        6,
        4,
        4,
        4,
        0
      ],
      [
        0,
        0,
        0,
        0,
        0,
        0,
        0,
        0,
        0,
        0,
        0,
        15,
        0,
        0,
        0,
        0,
        0,
        0,
        0,
        0,
        0,
        0
      ],
      [
        0,
        0,
        0,
        0,
        0,
        0,
        0,
        0,
        0,
        0,
        0,
        26,
        0,
        0,
        0,
        0,
        0,
        0,
        0,
        0,
        0,
        0
      ]
    ],
    [
      [
        0,
        0,
        0,
        0,
        0,
        0,
        0,
        0,
        0,
        0,
        0,
        0,
        0,
        0,
        0,
        0,
        0,
        0,
        0,
        0,
        0,
        0
      ],
      [
        0,
        0,
        0,
        0,
        0,
        0,
        0,
        0,
        0,
        0,
        0,
        0,
        0,
        0,
        0,
        0,
        0,
        0,
        0,
        0,
        0,
        0
      ],
      [
        0,
        0,
        0,
        0,
        0,
        0,
        0,
        0,
        0,
        0,
        0,
        27,
        0,
        0,
        0,
        0,
        28,
        6,
        4,
        29,
        4,
        0
      ],
      [
        0,
        0,
        0,
        0,
        0,
        0,
        0,
        0,
        0,
        0,
        0,
        0,
        0,
        0,
        0,
        0,
        0,
        4,
        7,
        7,
        7,
        4
      ],
      [
        0,
        0,
        0,
        0,
        0,
        0,
        0,
        0,
        0,
        0,
        0,
        0,
        0,
        0,
        0,
        0,
        0,
        4,
        7,
        7,
        7,
        4
      ],
      [
        1,
        2,
        2,
        2,
        23,
        0,
        0,
        0,
        0,
        0,
        0,
        0,
        0,
        6,
        0,
        0,
        0,
        0,
        7,
        7,
        7,
        6
      ],
      [
        0,
        0,
        0,
        0,
        0,
        0,
        0,
        0,
        0,
        0,
        0,
        0,
        0,
        0,
        0,
        0,
        0,
        4,
        7,
        7,
        7,
        4
      ],
      [
        0,
        0,
        0,
        0,
        0,
        0,
        0,
        0,
        0,
        0,
        0,
        0,
        0,
        0,
        0,
        0,
        0,
        4,
        7,
        7,
        7,
        4
      ],
      [
        0,
        0,
        0,
        0,
        0,
        0,
        0,
        0,
        0,
        0,
        0,
        30,
        0,
        0,
        0,
        0,
        28,
        6,
        4,
        29,
        4,
        0
      ],
      [
        0,
        0,
        0,
        0,
        0,
        0,
        0,
        0,
        0,
        0,
        0,
        0,
        0,
        0,
        0,
        0,
        0,
        0,
        0,
        0,
        0,
        0
      ],
      [
        0,
        0,
        0,
        0,
        0,
        0,
        0,
        0,
        0,
        0,
        0,
        0,
        0,
        0,
        0,
        0,
        0,
        0,
        0,
        0,
        0,
        0
      ]
    ],
    [
      [
        0,
        0,
        0,
        0,
        0,
        0,
        0,
        0,
        0,
        0,
        0,
        0,
        0,
        0,
        0,
        0,
        0,
        0,
        0,
        0,
        0,
        0
      ],
      [
        0,
        0,
        0,
        0,
        0,
        0,
        0,
        0,
        0,
        0,
        0,
        0,
        0,
        0,
        0,
        0,
        0,
        0,
        0,
        0,
        0,
        0
      ],
      [
        0,
        0,
        0,
        0,
        0,
        0,
        0,
        0,
        0,
        0,
        0,
        0,
        0,
        0,
        0,
        0,
        0,
        6,
        4,
        4,
        4,
        0
      ],
      [
        0,
        0,
        0,
        0,
        0,
        0,
        0,
        0,
        0,
        0,
        0,
        0,
        0,
        0,
        0,
        0,
        0,
        4,
        7,
        7,
        7,
        4
      ],
      [
        0,
        0,
        0,
        0,
        0,
        0,
        0,
        0,
        0,
        0,
        0,
        0,
        0,
        0,
        0,
        0,
        0,
        4,
        7,
        7,
        7,
        4
      ],
      [
        0,
        0,
        0,
        0,
        0,
        0,
        0,
        0,
        0,
        0,
        0,
        0,
        0,
        6,
        0,
        0,
        0,
        4,
        7,
        7,
        31,
        6
      ],
      [
        0,
        0,
        0,
        0,
        0,
        0,
        0,
        0,
        0,
        0,
        0,
        0,
        0,
        0,
        0,
        0,
        0,
        4,
        7,
        7,
        7,
        4
      ],
      [
        0,
        0,
        0,
        0,
        0,
        0,
        0,
        0,
        0,
        0,
        0,
        0,
        0,
        0,
        0,
        0,
        0,
        4,
        7,
        7,
        7,
        4
      ],
      [
        0,
        0,
        0,
        0,
        0,
        0,
        0,
        0,
        0,
        0,
        0,
        0,
        0,
        0,
        0,
        0,
        0,
        6,
        4,
        4,
        4,
        0
      ],
      [
        0,
        0,
        0,
        0,
        0,
        0,
        0,
        0,
        0,
        0,
        0,
        0,
        0,
        0,
        0,
        0,
        0,
        0,
        0,
        0,
        0,
        0
      ],
      [
        0,
        0,
        0,
        0,
        0,
        0,
        0,
        0,
        0,
        0,
        0,
        0,
        0,
        0,
        0,
        0,
        0,
        0,
        0,
        0,
        0,
        0
      ]
    ],
    [
      [
        0,
        0,
        0,
        0,
        0,
        0,
        0,
        0,
        0,
        0,
        0,
        0,
        0,
        0,
        0,
        0,
        0,
        0,
        0,
        0,
        0,
        0
      ],
      [
        0,
        0,
        0,
        0,
        0,
        0,
        0,
        0,
        0,
        0,
        0,
        0,
        0,
        0,
        0,
        0,
        0,
        0,
        0,
        0,
        0,
        0
      ],
      [
        0,
        0,
        0,
        0,
        0,
        0,
        0,
        0,
        0,
        0,
        0,
        0,
        0,
        0,
        0,
        0,
        0,
        6,
        2,
        2,
        2,
        0
      ],
      [
        0,
        0,
        0,
        0,
        0,
        0,
        0,
        0,
        0,
        0,
        0,
        0,
        0,
        0,
        0,
        0,
        0,
        12,
        4,
        4,
        4,
        12
      ],
      [
        0,
        0,
        0,
        0,
        0,
        0,
        0,
        0,
        0,
        0,
        0,
        0,
        0,
        0,
        0,
        0,
        0,
        12,
        4,
        4,
        4,
        12
      ],
      [
        0,
        0,
        0,
        0,
        0,
        0,
        0,
        0,
        0,
        0,
        0,
        0,
        0,
        6,
        0,
        0,
        0,
        12,
        4,
        4,
        4,
        6
      ],
      [
        0,
        0,
        0,
        0,
        0,
        0,
        0,
        0,
        0,
        0,
        0,
        0,
        0,
        0,
        0,
        0,
        0,
        12,
        4,
        4,
        4,
        12
      ],
      [
        0,
        0,
        0,
        0,
        0,
        0,
        0,
        0,
        0,
        0,
        0,
        0,
        0,
        0,
        0,
        0,
        0,
        12,
        4,
        4,
        4,
        12
      ],
      [
        0,
        0,
        0,
        0,
        0,
        0,
        0,
        0,
        0,
        0,
        0,
        0,
        0,
        0,
        0,
        0,
        0,
        6,
        2,
        2,
        2,
        0
      ],
      [
        0,
        0,
        0,
        0,
        0,
        0,
        0,
        0,
        0,
        0,
        0,
        0,
        0,
        0,
        0,
        0,
        0,
        0,
        0,
        0,
        0,
        0
      ],
      [
        0,
        0,
        0,
        0,
        0,
        0,
        0,
        0,
        0,
        0,
        0,
        0,
        0,
        0,
        0,
        0,
        0,
        0,
        0,
        0,
        0,
        0
      ]
    ],
    [
      [
        0,
        0,
        0,
        0,
        0,
        0,
        0,
        0,
        0,
        0,
        0,
        0,
        0,
        0,
        0,
        0,
        0,
        0,
        0,
        0,
        0,
        0
      ],
      [
        0,
        0,
        0,
        0,
        0,
        0,
        0,
        0,
        0,
        0,
        0,
        0,
        0,
        0,
        0,
        0,
        0,
        0,
        0,
        0,
        0,
        0
      ],
      [
        0,
        0,
        0,
        0,
        0,
        0,
        0,
        0,
        0,
        0,
        0,
        0,
        0,
        0,
        0,
        0,
        0,
        13,
        13,
        13,
        13,
        0
      ],
      [
        0,
        0,
        0,
        0,
        0,
        0,
        0,
        0,
        0,
        0,
        0,
        0,
        0,
        0,
        0,
        0,
        0,
        13,
        0,
        0,
        13,
        13
      ],
      [
        0,
        0,
        0,
        0,
        0,
        0,
        0,
        0,
        0,
        0,
        0,
        0,
        0,
        0,
        0,
        0,
        0,
        13,
        0,
        0,
        0,
        13
      ],
      [
        0,
        0,
        0,
        0,
        0,
        0,
        0,
        0,
        0,
        0,
        0,
        0,
        0,
        6,
        0,
        0,
        0,
        32,
        33,
        0,
        0,
        13
      ],
      [
        0,
        0,
        0,
        0,
        0,
        0,
        0,
        0,
        0,
        0,
        0,
        0,
        0,
        0,
        0,
        0,
        0,
        13,
        0,
        0,
        0,
        13
      ],
      [
        0,
        0,
        0,
        0,
        0,
        0,
        0,
        0,
        0,
        0,
        0,
        0,
        0,
        0,
        0,
        0,
        0,
        13,
        0,
        0,
        13,
        13
      ],
      [
        0,
        0,
        0,
        0,
        0,
        0,
        0,
        0,
        0,
        0,
        0,
        0,
        0,
        0,
        0,
        0,
        0,
        13,
        13,
        13,
        13,
        0
      ],
      [
        0,
        0,
        0,
        0,
        0,
        0,
        0,
        0,
        0,
        0,
        0,
        0,
        0,
        0,
        0,
        0,
        0,
        0,
        0,
        0,
        0,
        0
      ],
      [
        0,
        0,
        0,
        0,
        0,
        0,
        0,
        0,
        0,
        0,
        0,
        0,
        0,
        0,
        0,
        0,
        0,
        0,
        0,
        0,
        0,
        0
      ]
    ],
    [
      [
        0,
        0,
        0,
        0,
        0,
        0,
        0,
        0,
        0,
        0,
        0,
        0,
        0,
        0,
        0,
        0,
        0,
        0,
        0,
        0,
        0,
        0
      ],
      [
        0,
        0,
        0,
        0,
        0,
        0,
        0,
        0,
        0,
        0,
        0,
        0,
        0,
        0,
        0,
        0,
        0,
        0,
        0,
        0,
        0,
        0
      ],
      [
        0,
        0,
        0,
        0,
        0,
        0,
        0,
        0,
        0,
        0,
        0,
        0,
        0,
        0,
        0,
        0,
        0,
        0,
        0,
        0,
        0,
        0
      ],
      [
        0,
        0,
        0,
        0,
        0,
        0,
        0,
        0,
        0,
        0,
        0,
        0,
        0,
        0,
        0,
        0,
        0,
        0,
        0,
        0,
        0,
        0
      ],
      [
        0,
        0,
        0,
        0,
        0,
        0,
        0,
        0,
        0,
        0,
        0,
        0,
        0,
        0,
        0,
        0,
        0,
        0,
        0,
        0,
        0,
        0
      ],
      [
        0,
        0,
        0,
        0,
        0,
        0,
        0,
        0,
        0,
        0,
        0,
        0,
        0,
        6,
        0,
        0,
        0,
        0,
        0,
        0,
        0,
        0
      ],
      [
        0,
        0,
        0,
        0,
        0,
        0,
        0,
        0,
        0,
        0,
        0,
        0,
        0,
        0,
        0,
        0,
        0,
        0,
        0,
        0,
        0,
        0
      ],
      [
        0,
        0,
        0,
        0,
        0,
        0,
        0,
        0,
        0,
        0,
        0,
        0,
        0,
        0,
        0,
        0,
        0,
        0,
        0,
        0,
        0,
        0
      ],
      [
        0,
        0,
        0,
        0,
        0,
        0,
        0,
        0,
        0,
        0,
        0,
        0,
        0,
        0,
        0,
        0,
        0,
        0,
        0,
        0,
        0,
        0
      ],
      [
        0,
        0,
        0,
        0,
        0,
        0,
        0,
        0,
        0,
        0,
        0,
        0,
        0,
        0,
        0,
        0,
        0,
        0,
        0,
        0,
        0,
        0
      ],
      [
        0,
        0,
        0,
        0,
        0,
        0,
        0,
        0,
        0,
        0,
        0,
        0,
        0,
        0,
        0,
        0,
        0,
        0,
        0,
        0,
        0,
        0
      ]
    ],
    [
      [
        0,
        0,
        0,
        0,
        0,
        0,
        0,
        0,
        0,
        0,
        0,
        0,
        0,
        0,
        0,
        0,
        0,
        0,
        0,
        0,
        0,
        0
      ],
      [
        0,
        0,
        0,
        0,
        0,
        0,
        0,
        0,
        0,
        0,
        0,
        0,
        0,
        0,
        0,
        0,
        0,
        0,
        0,
        0,
        0,
        0
      ],
      [
        0,
        0,
        0,
        0,
        0,
        0,
        0,
        0,
        0,
        0,
        0,
        0,
        0,
        0,
        0,
        0,
        0,
        0,
        0,
        0,
        0,
        0
      ],
      [
        0,
        0,
        0,
        0,
        0,
        0,
        0,
        0,
        0,
        0,
        0,
        0,
        0,
        0,
        0,
        0,
        0,
        0,
        0,
        0,
        0,
        0
      ],
      [
        0,
        0,
        0,
        0,
        0,
        0,
        0,
        0,
        0,
        0,
        0,
        0,
        0,
        0,
        0,
        0,
        0,
        0,
        0,
        0,
        0,
        0
      ],
      [
        0,
        0,
        0,
        0,
        0,
        0,
        0,
        0,
        0,
        0,
        0,
        0,
        0,
        6,
        0,
        0,
        0,
        0,
        0,
        0,
        0,
        0
      ],
      [
        0,
        0,
        0,
        0,
        0,
        0,
        0,
        0,
        0,
        0,
        0,
        0,
        0,
        0,
        0,
        0,
        0,
        0,
        0,
        0,
        0,
        0
      ],
      [
        0,
        0,
        0,
        0,
        0,
        0,
        0,
        0,
        0,
        0,
        0,
        0,
        0,
        0,
        0,
        0,
        0,
        0,
        0,
        0,
        0,
        0
      ],
      [
        0,
        0,
        0,
        0,
        0,
        0,
        0,
        0,
        0,
        0,
        0,
        0,
        0,
        0,
        0,
        0,
        0,
        0,
        0,
        0,
        0,
        0
      ],
      [
        0,
        0,
        0,
        0,
        0,
        0,
        0,
        0,
        0,
        0,
        0,
        0,
        0,
        0,
        0,
        0,
        0,
        0,
        0,
        0,
        0,
        0
      ],
      [
        0,
        0,
        0,
        0,
        0,
        0,
        0,
        0,
        0,
        0,
        0,
        0,
        0,
        0,
        0,
        0,
        0,
        0,
        0,
        0,
        0,
        0
      ]
    ],
    [
      [
        0,
        0,
        0,
        0,
        0,
        0,
        0,
        0,
        0,
        0,
        0,
        0,
        0,
        0,
        0,
        0,
        0,
        0,
        0,
        0,
        0,
        0
      ],
      [
        0,
        0,
        0,
        0,
        0,
        0,
        0,
        0,
        0,
        0,
        0,
        0,
        0,
        0,
        0,
        0,
        0,
        0,
        0,
        0,
        0,
        0
      ],
      [
        0,
        0,
        0,
        0,
        0,
        0,
        0,
        0,
        0,
        0,
        0,
        0,
        0,
        0,
        0,
        0,
        0,
        0,
        0,
        0,
        0,
        0
      ],
      [
        0,
        0,
        0,
        0,
        0,
        0,
        0,
        0,
        0,
        0,
        0,
        0,
        0,
        0,
        0,
        0,
        0,
        0,
        0,
        0,
        0,
        0
      ],
      [
        0,
        0,
        0,
        0,
        0,
        0,
        0,
        0,
        0,
        0,
        0,
        0,
        0,
        0,
        0,
        0,
        0,
        0,
        0,
        0,
        0,
        0
      ],
      [
        0,
        0,
        0,
        0,
        0,
        0,
        0,
        0,
        0,
        0,
        0,
        0,
        0,
        6,
        0,
        0,
        0,
        0,
        0,
        0,
        0,
        0
      ],
      [
        0,
        0,
        0,
        0,
        0,
        0,
        0,
        0,
        0,
        0,
        0,
        0,
        0,
        0,
        0,
        0,
        0,
        0,
        0,
        0,
        0,
        0
      ],
      [
        0,
        0,
        0,
        0,
        0,
        0,
        0,
        0,
        0,
        0,
        0,
        0,
        0,
        0,
        0,
        0,
        0,
        0,
        0,
        0,
        0,
        0
      ],
      [
        0,
        0,
        0,
        0,
        0,
        0,
        0,
        0,
        0,
        0,
        0,
        0,
        0,
        0,
        0,
        0,
        0,
        0,
        0,
        0,
        0,
        0
      ],
      [
        0,
        0,
        0,
        0,
        0,
        0,
        0,
        0,
        0,
        0,
        0,
        0,
        0,
        0,
        0,
        0,
        0,
        0,
        0,
        0,
        0,
        0
      ],
      [
        0,
        0,
        0,
        0,
        0,
        0,
        0,
        0,
        0,
        0,
        0,
        0,
        0,
        0,
        0,
        0,
        0,
        0,
        0,
        0,
        0,
        0
      ]
    ],
    [
      [
        0,
        0,
        0,
        0,
        0,
        0,
        0,
        0,
        0,
        0,
        0,
        0,
        0,
        0,
        0,
        0,
        0,
        0,
        0,
        0,
        0,
        0
      ],
      [
        0,
        0,
        0,
        0,
        0,
        0,
        0,
        0,
        0,
        0,
        0,
        0,
        0,
        0,
        0,
        0,
        0,
        0,
        0,
        0,
        0,
        0
      ],
      [
        0,
        0,
        0,
        0,
        0,
        0,
        0,
        0,
        0,
        0,
        0,
        0,
        0,
        0,
        0,
        0,
        0,
        0,
        0,
        0,
        0,
        0
      ],
      [
        0,
        0,
        0,
        0,
        0,
        0,
        0,
        0,
        0,
        0,
        0,
        0,
        0,
        0,
        0,
        0,
        0,
        0,
        0,
        0,
        0,
        0
      ],
      [
        0,
        0,
        0,
        0,
        0,
        0,
        0,
        0,
        0,
        0,
        0,
        0,
        0,
        0,
        0,
        0,
        0,
        0,
        0,
        0,
        0,
        0
      ],
      [
        0,
        0,
        0,
        0,
        0,
        0,
        0,
        0,
        0,
        0,
        0,
        0,
        0,
        6,
        0,
        0,
        0,
        0,
        0,
        0,
        0,
        0
      ],
      [
        0,
        0,
        0,
        0,
        0,
        0,
        0,
        0,
        0,
        0,
        0,
        0,
        0,
        0,
        0,
        0,
        0,
        0,
        0,
        0,
        0,
        0
      ],
      [
        0,
        0,
        0,
        0,
        0,
        0,
        0,
        0,
        0,
        0,
        0,
        0,
        0,
        0,
        0,
        0,
        0,
        0,
        0,
        0,
        0,
        0
      ],
      [
        0,
        0,
        0,
        0,
        0,
        0,
        0,
        0,
        0,
        0,
        0,
        0,
        0,
        0,
        0,
        0,
        0,
        0,
        0,
        0,
        0,
        0
      ],
      [
        0,
        0,
        0,
        0,
        0,
        0,
        0,
        0,
        0,
        0,
        0,
        0,
        0,
        0,
        0,
        0,
        0,
        0,
        0,
        0,
        0,
        0
      ],
      [
        0,
        0,
        0,
        0,
        0,
        0,
        0,
        0,
        0,
        0,
        0,
        0,
        0,
        0,
        0,
        0,
        0,
        0,
        0,
        0,
        0,
        0
      ]
    ],
    [
      [
        0,
        0,
        0,
        0,
        0,
        0,
        0,
        0,
        0,
        0,
        0,
        0,
        0,
        12,
        0,
        0,
        0,
        0,
        0,
        0,
        0,
        0
      ],
      [
        0,
        0,
        0,
        0,
        0,
        0,
        0,
        0,
        0,
        0,
        0,
        0,
        0,
        12,
        0,
        0,
        0,
        0,
        0,
        0,
        0,
        0
      ],
      [
        0,
        0,
        0,
        0,
        0,
        0,
        0,
        0,
        0,
        0,
        0,
        0,
        0,
        12,
        0,
        0,
        0,
        0,
        0,
        0,
        0,
        0
      ],
      [
        0,
        0,
        0,
        0,
        0,
        0,
        0,
        0,
        0,
        0,
        0,
        0,
        0,
        12,
        0,
        0,
        0,
        0,
        0,
        0,
        0,
        0
      ],
      [
        0,
        0,
        0,
        0,
        0,
        0,
        0,
        0,
        0,
        0,
        0,
        0,
        0,
        12,
        0,
        0,
        0,
        0,
        0,
        0,
        0,
        0
      ],
      [
        0,
        0,
        0,
        0,
        0,
        0,
        0,
        0,
        0,
        0,
        0,
        0,
        0,
        6,
        0,
        0,
        0,
        0,
        0,
        0,
        0,
        0
      ],
      [
        0,
        0,
        0,
        0,
        0,
        0,
        0,
        0,
        0,
        0,
        0,
        0,
        0,
        12,
        0,
        0,
        0,
        0,
        0,
        0,
        0,
        0
      ],
      [
        0,
        0,
        0,
        0,
        0,
        0,
        0,
        0,
        0,
        0,
        0,
        0,
        0,
        12,
        0,
        0,
        0,
        0,
        0,
        0,
        0,
        0
      ],
      [
        0,
        0,
        0,
        0,
        0,
        0,
        0,
        0,
        0,
        0,
        0,
        0,
        0,
        12,
        0,
        0,
        0,
        0,
        0,
        0,
        0,
        0
      ],
      [
        0,
        0,
        0,
        0,
        0,
        0,
        0,
        0,
        0,
        0,
        0,
        0,
        0,
        12,
        0,
        0,
        0,
        0,
        0,
        0,
        0,
        0
      ],
      [
        0,
        0,
        0,
        0,
        0,
        0,
        0,
        0,
        0,
        0,
        0,
        0,
        0,
        12,
        0,
        0,
        0,
        0,
        0,
        0,
        0,
        0
      ]
    ],
    [
      [
        0,
        0,
        0,
        0,
        0,
        0,
        0,
        0,
        0,
        0,
        0,
        0,
        0,
        0,
        0,
        0,
        0,
        0,
        0,
        0,
        0,
        0
      ],
      [
        0,
        0,
        0,
        0,
        0,
        0,
        0,
        0,
        0,
        0,
        0,
        0,
        0,
        0,
        0,
        0,
        0,
        0,
        0,
        0,
        0,
        0
      ],
      [
        0,
        0,
        0,
        0,
        0,
        0,
        0,
        0,
        0,
        0,
        0,
        0,
        0,
        0,
        0,
        0,
        0,
        0,
        0,
        0,
        0,
        0
      ],
      [
        0,
        0,
        0,
        0,
        0,
        0,
        0,
        0,
        0,
        0,
        0,
        0,
        0,
        0,
        0,
        0,
        0,
        0,
        0,
        0,
        0,
        0
      ],
      [
        0,
        0,
        0,
        0,
        0,
        0,
        0,
        0,
        0,
        0,
        0,
        0,
        0,
        0,
        0,
        0,
        0,
        0,
        0,
        0,
        0,
        0
      ],
      [
        0,
        0,
        0,
        0,
        0,
        0,
        0,
        0,
        0,
        0,
        0,
        0,
        0,
        6,
        0,
        0,
        0,
        0,
        0,
        0,
        0,
        0
      ],
      [
        0,
        0,
        0,
        0,
        0,
        0,
        0,
        0,
        0,
        0,
        0,
        0,
        0,
        0,
        0,
        0,
        0,
        0,
        0,
        0,
        0,
        0
      ],
      [
        0,
        0,
        0,
        0,
        0,
        0,
        0,
        0,
        0,
        0,
        0,
        0,
        0,
        0,
        0,
        0,
        0,
        0,
        0,
        0,
        0,
        0
      ],
      [
        0,
        0,
        0,
        0,
        0,
        0,
        0,
        0,
        0,
        0,
        0,
        0,
        0,
        0,
        0,
        0,
        0,
        0,
        0,
        0,
        0,
        0
      ],
      [
        0,
        0,
        0,
        0,
        0,
        0,
        0,
        0,
        0,
        0,
        0,
        0,
        0,
        0,
        0,
        0,
        0,
        0,
        0,
        0,
        0,
        0
      ],
      [
        0,
        0,
        0,
        0,
        0,
        0,
        0,
        0,
        0,
        0,
        0,
        0,
        0,
        0,
        0,
        0,
        0,
        0,
        0,
        0,
        0,
        0
      ]
    ],
    [
      [
        0,
        0,
        0,
        0,
        0,
        0,
        0,
        0,
        0,
        0,
        0,
        0,
        0,
        0,
        0,
        0,
        0,
        0,
        0,
        0,
        0,
        0
      ],
      [
        0,
        0,
        0,
        0,
        0,
        0,
        0,
        0,
        0,
        0,
        0,
        0,
        0,
        0,
        0,
        0,
        0,
        0,
        0,
        0,
        0,
        0
      ],
      [
        0,
        0,
        0,
        0,
        0,
        0,
        0,
        0,
        0,
        0,
        0,
        0,
        0,
        0,
        0,
        0,
        0,
        0,
        0,
        0,
        0,
        0
      ],
      [
        0,
        0,
        0,
        0,
        0,
        0,
        0,
        0,
        0,
        0,
        0,
        0,
        0,
        0,
        0,
        0,
        0,
        0,
        0,
        0,
        0,
        0
      ],
      [
        0,
        0,
        0,
        0,
        0,
        0,
        0,
        0,
        0,
        0,
        0,
        0,
        34,
        34,
        34,
        0,
        0,
        0,
        0,
        0,
        0,
        0
      ],
      [
        0,
        0,
        0,
        0,
        0,
        0,
        0,
        0,
        0,
        0,
        0,
        0,
        34,
        6,
        34,
        0,
        0,
        0,
        0,
        0,
        0,
        0
      ],
      [
        0,
        0,
        0,
        0,
        0,
        0,
        0,
        0,
        0,
        0,
        0,
        0,
        34,
        34,
        34,
        0,
        0,
        0,
        0,
        0,
        0,
        0
      ],
      [
        0,
        0,
        0,
        0,
        0,
        0,
        0,
        0,
        0,
        0,
        0,
        0,
        0,
        0,
        0,
        0,
        0,
        0,
        0,
        0,
        0,
        0
      ],
      [
        0,
        0,
        0,
        0,
        0,
        0,
        0,
        0,
        0,
        0,
        0,
        0,
        0,
        0,
        0,
        0,
        0,
        0,
        0,
        0,
        0,
        0
      ],
      [
        0,
        0,
        0,
        0,
        0,
        0,
        0,
        0,
        0,
        0,
        0,
        0,
        0,
        0,
        0,
        0,
        0,
        0,
        0,
        0,
        0,
        0
      ],
      [
        0,
        0,
        0,
        0,
        0,
        0,
        0,
        0,
        0,
        0,
        0,
        0,
        0,
        0,
        0,
        0,
        0,
        0,
        0,
        0,
        0,
        0
      ]
    ],
    [
      [
        0,
        0,
        0,
        0,
        0,
        0,
        0,
        0,
        0,
        0,
        0,
        0,
        0,
        0,
        0,
        0,
        0,
        0,
        0,
        0,
        0,
        0
      ],
      [
        0,
        0,
        0,
        0,
        0,
        0,
        0,
        0,
        0,
        0,
        0,
        0,
        0,
        0,
        0,
        0,
        0,
        0,
        0,
        0,
        0,
        0
      ],
      [
        0,
        0,
        0,
        0,
        0,
        0,
        0,
        0,
        0,
        0,
        0,
        0,
        0,
        0,
        0,
        0,
        0,
        0,
        0,
        0,
        0,
        0
      ],
      [
        0,
        0,
        0,
        0,
        0,
        0,
        0,
        0,
        0,
        0,
        0,
        0,
        0,
        0,
        0,
        0,
        0,
        0,
        0,
        0,
        0,
        0
      ],
      [
        0,
        0,
        0,
        0,
        0,
        0,
        0,
        0,
        0,
        0,
        0,
        0,
        0,
        0,
        0,
        0,
        0,
        0,
        0,
        0,
        0,
        0
      ],
      [
        0,
        0,
        0,
        0,
        0,
        0,
        0,
        0,
        0,
        0,
        0,
        0,
        0,
        6,
        0,
        0,
        0,
        0,
        0,
        0,
        0,
        0
      ],
      [
        0,
        0,
        0,
        0,
        0,
        0,
        0,
        0,
        0,
        0,
        0,
        0,
        0,
        0,
        0,
        0,
        0,
        0,
        0,
        0,
        0,
        0
      ],
      [
        0,
        0,
        0,
        0,
        0,
        0,
        0,
        0,
        0,
        0,
        0,
        0,
        0,
        0,
        0,
        0,
        0,
        0,
        0,
        0,
        0,
        0
      ],
      [
        0,
        0,
        0,
        0,
        0,
        0,
        0,
        0,
        0,
        0,
        0,
        0,
        0,
        0,
        0,
        0,
        0,
        0,
        0,
        0,
        0,
        0
      ],
      [
        0,
        0,
        0,
        0,
        0,
        0,
        0,
        0,
        0,
        0,
        0,
        0,
        0,
        0,
        0,
        0,
        0,
        0,
        0,
        0,
        0,
        0
      ],
      [
        0,
        0,
        0,
        0,
        0,
        0,
        0,
        0,
        0,
        0,
        0,
        0,
        0,
        0,
        0,
        0,
        0,
        0,
        0,
        0,
        0,
        0
      ]
    ],
    [
      [
        0,
        0,
        0,
        0,
        0,
        0,
        0,
        0,
        0,
        0,
        0,
        0,
        0,
        0,
        0,
        0,
        0,
        0,
        0,
        0,
        0,
        0
      ],
      [
        0,
        0,
        0,
        0,
        0,
        0,
        0,
        0,
        0,
        0,
        0,
        0,
        0,
        0,
        0,
        0,
        0,
        0,
        0,
        0,
        0,
        0
      ],
      [
        0,
        0,
        0,
        0,
        0,
        0,
        0,
        0,
        0,
        0,
        0,
        0,
        0,
        0,
        0,
        0,
        0,
        0,
        0,
        0,
        0,
        0
      ],
      [
        0,
        0,
        0,
        0,
        0,
        0,
        0,
        0,
        0,
        0,
        0,
        0,
        0,
        0,
        0,
        0,
        0,
        0,
        0,
        0,
        0,
        0
      ],
      [
        0,
        0,
        0,
        0,
        0,
        0,
        0,
        0,
        0,
        0,
        0,
        0,
        0,
        0,
        0,
        0,
        0,
        0,
        0,
        0,
        0,
        0
      ],
      [
        0,
        0,
        0,
        0,
        0,
        0,
        0,
        0,
        0,
        0,
        0,
        0,
        0,
        6,
        0,
        0,
        0,
        0,
        0,
        0,
        0,
        0
      ],
      [
        0,
        0,
        0,
        0,
        0,
        0,
        0,
        0,
        0,
        0,
        0,
        0,
        0,
        0,
        0,
        0,
        0,
        0,
        0,
        0,
        0,
        0
      ],
      [
        0,
        0,
        0,
        0,
        0,
        0,
        0,
        0,
        0,
        0,
        0,
        0,
        0,
        0,
        0,
        0,
        0,
        0,
        0,
        0,
        0,
        0
      ],
      [
        0,
        0,
        0,
        0,
        0,
        0,
        0,
        0,
        0,
        0,
        0,
        0,
        0,
        0,
        0,
        0,
        0,
        0,
        0,
        0,
        0,
        0
      ],
      [
        0,
        0,
        0,
        0,
        0,
        0,
        0,
        0,
        0,
        0,
        0,
        0,
        0,
        0,
        0,
        0,
        0,
        0,
        0,
        0,
        0,
        0
      ],
      [
        0,
        0,
        0,
        0,
        0,
        0,
        0,
        0,
        0,
        0,
        0,
        0,
        0,
        0,
        0,
        0,
        0,
        0,
        0,
        0,
        0,
        0
      ]
    ],
    [
      [
        0,
        0,
        0,
        0,
        0,
        0,
        0,
        0,
        0,
        0,
        0,
        0,
        0,
        0,
        0,
        0,
        0,
        0,
        0,
        0,
        0,
        0
      ],
      [
        0,
        0,
        0,
        0,
        0,
        0,
        0,
        0,
        0,
        0,
        0,
        0,
        0,
        0,
        0,
        0,
        0,
        0,
        0,
        0,
        0,
        0
      ],
      [
        0,
        0,
        0,
        0,
        0,
        0,
        0,
        0,
        0,
        0,
        0,
        0,
        0,
        0,
        0,
        0,
        0,
        0,
        0,
        0,
        0,
        0
      ],
      [
        0,
        0,
        0,
        0,
        0,
        0,
        0,
        0,
        0,
        0,
        0,
        0,
        0,
        0,
        0,
        0,
        0,
        0,
        0,
        0,
        0,
        0
      ],
      [
        0,
        0,
        0,
        0,
        0,
        0,
        0,
        0,
        0,
        0,
        0,
        0,
        0,
        0,
        0,
        0,
        0,
        0,
        0,
        0,
        0,
        0
      ],
      [
        0,
        0,
        0,
        0,
        0,
        0,
        0,
        0,
        0,
        0,
        0,
        0,
        0,
        6,
        0,
        0,
        0,
        0,
        0,
        0,
        0,
        0
      ],
      [
        0,
        0,
        0,
        0,
        0,
        0,
        0,
        0,
        0,
        0,
        0,
        0,
        0,
        0,
        0,
        0,
        0,
        0,
        0,
        0,
        0,
        0
      ],
      [
        0,
        0,
        0,
        0,
        0,
        0,
        0,
        0,
        0,
        0,
        0,
        0,
        0,
        0,
        0,
        0,
        0,
        0,
        0,
        0,
        0,
        0
      ],
      [
        0,
        0,
        0,
        0,
        0,
        0,
        0,
        0,
        0,
        0,
        0,
        0,
        0,
        0,
        0,
        0,
        0,
        0,
        0,
        0,
        0,
        0
      ],
      [
        0,
        0,
        0,
        0,
        0,
        0,
        0,
        0,
        0,
        0,
        0,
        0,
        0,
        0,
        0,
        0,
        0,
        0,
        0,
        0,
        0,
        0
      ],
      [
        0,
        0,
        0,
        0,
        0,
        0,
        0,
        0,
        0,
        0,
        0,
        0,
        0,
        0,
        0,
        0,
        0,
        0,
        0,
        0,
        0,
        0
      ]
    ]
  ],
  "topConnectorCoords" : null,
  "bottomConnectorCoords" : null,
  "northConnectorCoords" : null,
  "southConnectorCoords" : null,
  "westConnectorCoords" : null,
  "eastConnectorCoords" : null,
  "treasureChestCoords" : {
    "x" : 8,
    "y" : 3,
    "z" : 5
  },
  "spawnerCoords" : [
    {
      "x" : 9,
      "y" : 2,
      "z" : 5
    }
  ],
  "unique" : false
}